{"skeleton":{"width":229.86,"height":164.62,"fps":24,"hash":" ","name":"Armature"},"bones":[{"name":"root"},{"length":102,"x":15,"y":53,"rotation":115.0622,"name":"body","parent":"root"},{"x":-51.9643,"y":-1.8552,"name":"bone_ikTarget2","parent":"root"},{"x":-26.819,"y":-0.3276,"name":"bone_ikTarget1","parent":"root"},{"x":15.9068,"y":1.9771,"name":"bone_ikTarget","parent":"root"},{"x":69.6592,"y":3.6916,"name":"bone_ikTarget3","parent":"root"},{"length":55,"x":26.6786,"y":15.5663,"rotation":67.4449,"name":"legtop4","parent":"body"},{"length":59,"x":29.8979,"y":34.1731,"rotation":14.8668,"name":"legtop3","parent":"body"},{"length":55,"x":6.2407,"y":-4.9667,"rotation":-128.5189,"name":"legtop2","parent":"body"},{"length":54,"x":14.4222,"y":-30.4934,"rotation":-121.3095,"name":"legtop","parent":"body"},{"length":57,"x":19.4091,"y":30.3021,"rotation":45.1053,"name":"legtop1","parent":"body"},{"length":50,"x":35.4489,"y":-49.15,"rotation":-77.8255,"name":"legtop41","parent":"body"},{"length":78,"x":54.9297,"y":0.6238,"rotation":117.0128,"name":"legbottom11","parent":"legtop4"},{"length":72,"x":56.1426,"y":0.0725,"rotation":-127.0558,"name":"legbottom","parent":"legtop2"},{"length":76,"x":59.9227,"y":-0.5577,"rotation":111.3813,"name":"legbottom111","parent":"legtop3"},{"length":81,"x":55.4057,"y":0.143,"rotation":124.7668,"name":"legbottom1","parent":"legtop1"},{"length":72,"x":51.9708,"y":-0.1961,"rotation":-136.2991,"name":"legbottom2","parent":"legtop41"},{"length":73,"x":53.1862,"y":0.7639,"rotation":-99.4964,"name":"legbottom1111","parent":"legtop"}],"slots":[{"name":"legbottom","bone":"legbottom","attachment":"legbottom"},{"name":"legtop","bone":"legtop","attachment":"legtop"},{"name":"legtop1","bone":"legtop1","attachment":"legtop"},{"name":"legtop2","bone":"legtop2","attachment":"legtop"},{"name":"legtop4","bone":"legtop4","attachment":"legtop"},{"name":"legbottom1","bone":"legbottom1","attachment":"legbottom"},{"name":"legbottom11","bone":"legbottom11","attachment":"legbottom"},{"name":"legbottom1111","bone":"legbottom1111","attachment":"legbottom"},{"name":"legbottom2","bone":"legbottom2","attachment":"legbottom"},{"name":"legtop41","bone":"legtop41","attachment":"legtop"},{"name":"legbottom111","bone":"legbottom111","attachment":"legbottom"},{"name":"legtop3","bone":"legtop3","attachment":"legtop"},{"name":"body","bone":"body","attachment":"body"}],"ik":[{"bendPositive":false,"name":"bone_ik1","target":"bone_ikTarget1","bones":["legbottom11"]},{"bendPositive":false,"name":"bone_ik","target":"bone_ikTarget","bones":["legbottom"]},{"bendPositive":false,"name":"bone_ik2","target":"bone_ikTarget2","bones":["legbottom1"]},{"bendPositive":false,"name":"bone_ik3","target":"bone_ikTarget3","bones":["legbottom1111"]}],"skins":{"default":{"legbottom1":{"legbottom":{"name":"legbottom","width":74,"height":69,"x":43.28,"y":5.62,"rotation":52.78}},"legtop2":{"legtop":{"name":"legtop","width":28,"height":60,"x":30.53,"y":0.67,"rotation":-70.43,"scaleX":-1}},"legtop41":{"legtop":{"name":"legtop","width":28,"height":60,"x":28.28,"y":-1.12,"rotation":-71.55,"scaleX":-1}},"legtop1":{"legtop":{"name":"legtop","width":28,"height":60,"x":28.69,"y":1.04,"rotation":-113.49}},"body":{"body":{"name":"body","width":137,"height":127,"x":40.33,"y":-9.28,"rotation":-128.9}},"legtop":{"legtop":{"name":"legtop","width":28,"height":60,"x":27.85,"y":-0.34,"rotation":-72.71,"scaleX":-1}},"legbottom1111":{"legbottom":{"name":"legbottom","width":74,"height":69,"x":38.67,"y":-6.56,"rotation":127.72,"scaleX":-1}},"legtop3":{"legtop":{"name":"legtop","width":28,"height":60,"x":29.98,"y":1.13,"rotation":-109.83}},"legtop4":{"legtop":{"name":"legtop","width":28,"height":60,"x":27.52,"y":-1.09,"rotation":-108.92}},"legbottom11":{"legbottom":{"name":"legbottom","width":74,"height":69,"x":42.04,"y":6.72,"rotation":53.23}},"legbottom2":{"legbottom":{"name":"legbottom","width":74,"height":69,"x":37.78,"y":-5.93,"rotation":127.99,"scaleX":-1}},"legbottom":{"legbottom":{"name":"legbottom","width":74,"height":69,"x":38.32,"y":-4.47,"rotation":126.2,"scaleX":-1}},"legbottom111":{"legbottom":{"name":"legbottom","width":74,"height":69,"x":40.76,"y":5.19,"rotation":50.61}}}},"animations":{"idle":{"bones":{"body":{"translate":[{"time":0},{"time":1,"x":-5,"y":-4},{"time":2}],"rotate":[{"time":0,"angle":0},{"time":1,"angle":2.28},{"time":2,"angle":0}],"shear":[{"time":0},{"time":1},{"time":2}]},"legtop3":{"rotate":[{"time":0,"angle":0},{"time":1,"angle":-2.01},{"time":2,"angle":0}],"shear":[{"time":0},{"time":1},{"time":2}]},"legbottom111":{"rotate":[{"time":0,"angle":0},{"time":1,"angle":-4.38},{"time":2,"angle":0}],"shear":[{"time":0},{"time":1},{"time":2}]},"legtop41":{"rotate":[{"time":0,"angle":0},{"time":1,"angle":-12.41},{"time":2,"angle":0}],"shear":[{"time":0},{"time":1},{"time":2}]},"legbottom2":{"rotate":[{"time":0,"angle":0},{"time":1,"angle":8.78},{"time":2,"angle":0}],"shear":[{"time":0},{"time":1},{"time":2}]}}},"shiver":{"bones":{"body":{"translate":[{"time":0},{"time":0.4167,"x":-2.5},{"time":0.5,"x":3.04},{"time":0.5833,"x":-2.47},{"time":0.6666,"x":3.02},{"time":0.7499,"x":-1.48},{"time":0.9999}]},"legtop3":{"rotate":[{"time":0,"angle":0},{"time":0.25,"angle":42.82},{"time":0.8333,"angle":42.82},{"time":1,"angle":0}],"shear":[{"time":0},{"time":0.25},{"time":0.8333},{"time":1}]},"legtop41":{"rotate":[{"time":0,"angle":0},{"time":0.25,"angle":-76.87},{"time":0.8333,"angle":-76.87},{"time":1,"angle":0}],"shear":[{"time":0},{"time":0.25},{"time":0.8333},{"time":1}]},"legbottom111":{"rotate":[{"time":0,"angle":0},{"time":0.25,"angle":-21.26},{"time":0.8333,"angle":-21.26},{"time":1,"angle":0}],"shear":[{"time":0},{"time":0.25},{"time":0.8333},{"time":1}]},"legbottom2":{"rotate":[{"time":0,"angle":0},{"time":0.25,"angle":87.07},{"time":0.8333,"angle":87.07},{"time":1,"angle":0}],"shear":[{"time":0},{"time":0.25},{"time":0.8333},{"time":1}]}}},"strike":{"bones":{"body":{"translate":[{"time":0},{"time":0.1667,"x":-2.5,"y":1.25},{"time":0.5}],"rotate":[{"time":0,"angle":0},{"time":0.25,"angle":5.54},{"time":0.5,"angle":0}],"shear":[{"time":0},{"time":0.25},{"time":0.5}]},"legtop3":{"rotate":[{"time":0,"angle":0},{"time":0.1667,"angle":-8.62},{"time":0.25,"angle":49.67},{"time":0.5,"angle":0}],"shear":[{"time":0},{"time":0.1667},{"time":0.25},{"time":0.5}]},"legtop41":{"rotate":[{"time":0,"angle":0},{"time":0.25,"angle":-35.73},{"time":0.5,"angle":0}],"shear":[{"time":0},{"time":0.25},{"time":0.5}]},"legbottom111":{"rotate":[{"time":0,"angle":0},{"time":0.1667,"angle":-79.31},{"time":0.25,"angle":-98.4},{"time":0.5,"angle":0}],"shear":[{"time":0},{"time":0.1667},{"time":0.25},{"time":0.5}]}}},"bite":{"bones":{"body":{"translate":[{"time":0},{"time":0.1667,"x":-3.75,"y":7.5},{"time":0.25,"x":-11.88,"y":3.75},{"time":0.5}],"rotate":[{"time":0,"angle":0},{"time":0.1667,"angle":-11.7},{"time":0.25,"angle":5.75},{"time":0.5,"angle":0}],"shear":[{"time":0},{"time":0.1667},{"time":0.25},{"time":0.5}]},"legtop4":{"rotate":[{"time":0,"angle":0},{"time":0.1667,"angle":32.97},{"time":0.5,"angle":0}],"shear":[{"time":0},{"time":0.1667},{"time":0.5}]},"legtop3":{"rotate":[{"time":0,"angle":0},{"time":0.1667,"angle":56.53},{"time":0.25,"angle":64.77},{"time":0.5,"angle":0}],"shear":[{"time":0},{"time":0.1667},{"time":0.25},{"time":0.5}]},"legtop1":{"rotate":[{"time":0,"angle":0},{"time":0.1667,"angle":28.67},{"time":0.5,"angle":0}],"shear":[{"time":0},{"time":0.1667},{"time":0.5}]},"legtop41":{"rotate":[{"time":0,"angle":0},{"time":0.1667,"angle":-36.41},{"time":0.5,"angle":0}],"shear":[{"time":0},{"time":0.1667},{"time":0.5}]},"legbottom2":{"rotate":[{"time":0,"angle":0},{"time":0.1667,"angle":41.59},{"time":0.5,"angle":0}],"shear":[{"time":0},{"time":0.1667},{"time":0.5}]}}},"oof":{"bones":{"body":{"translate":[{"time":0},{"time":0.125,"x":6.25},{"time":0.5}],"rotate":[{"time":0,"angle":0},{"time":0.125,"angle":-14.52},{"time":0.5,"angle":0}],"shear":[{"time":0},{"time":0.125},{"time":0.5}]},"legtop4":{"rotate":[{"time":0,"angle":0},{"time":0.125,"angle":17.52},{"time":0.5,"angle":0}],"shear":[{"time":0},{"time":0.125},{"time":0.5}]},"legtop3":{"rotate":[{"time":0,"angle":0},{"time":0.125,"angle":31.16},{"time":0.5,"angle":0}],"shear":[{"time":0},{"time":0.125},{"time":0.5}]},"legtop2":{"rotate":[{"time":0,"angle":0},{"time":0.125,"angle":9.47},{"time":0.5,"angle":0}],"shear":[{"time":0},{"time":0.125},{"time":0.5}]},"legtop":{"rotate":[{"time":0,"angle":0},{"time":0.125,"angle":19.13},{"time":0.5,"angle":0}],"shear":[{"time":0},{"time":0.125},{"time":0.5}]},"legtop1":{"rotate":[{"time":0,"angle":0},{"time":0.125,"angle":23.31},{"time":0.5,"angle":0}],"shear":[{"time":0},{"time":0.125},{"time":0.5}]},"legtop41":{"rotate":[{"time":0,"angle":0},{"time":0.125,"angle":-31.42},{"time":0.5,"angle":0}],"shear":[{"time":0},{"time":0.125},{"time":0.5}]},"legbottom111":{"rotate":[{"time":0,"angle":0},{"time":0.125,"angle":-20.09},{"time":0.5,"angle":0}],"shear":[{"time":0},{"time":0.125},{"time":0.5}]}}}}}